<?xml version="1.0" encoding="utf-8"?>
<search>
  
  
  
  <entry>
    <title>Github Pages + Hexo 搭建个人博客</title>
    <link href="/2021/10/14/GithubPages%20+%20Hexo%20%E6%90%AD%E5%BB%BA%E4%B8%AA%E4%BA%BA%E5%8D%9A%E5%AE%A2/"/>
    <url>/2021/10/14/GithubPages%20+%20Hexo%20%E6%90%AD%E5%BB%BA%E4%B8%AA%E4%BA%BA%E5%8D%9A%E5%AE%A2/</url>
    
    <content type="html"><![CDATA[<center>第一章 Github Pages</center><br><br>一、    新建Repository，存放项目文件<br><br>![avatar](images/ch1/1.png)<br><br>Repository name建议使用用户名.github.io<br><br>![avatar](images/ch1/2.png)]]></content>
    
    
    
  </entry>
  
  
  
  
</search>
